LICENSE
README.md
pylint_plugin_utils/__init__.py
pylint_plugin_utils-0.8.dist-info/LICENSE
pylint_plugin_utils-0.8.dist-info/WHEEL
pylint_plugin_utils-0.8.dist-info/METADATA
pylint_plugin_utils-0.8.dist-info/RECORD
