Metadata-Version: 2.1
Name: pylint-plugin-utils
Version: 0.8
Summary: Utilities and helpers for writing Pylint plugins
Home-page: https://github.com/PyCQA/pylint-plugin-utils
License: GPLv2
Keywords: pylint,plugin,helpers
Author: Carl Crowder
Author-email: git@carlcrowder.com
Requires-Python: >=3.7,<4.0
Classifier: License :: Other/Proprietary License
Classifier: Programming Language :: Python :: 3
Classifier: Programming Language :: Python :: 3.7
Classifier: Programming Language :: Python :: 3.8
Classifier: Programming Language :: Python :: 3.9
Classifier: Programming Language :: Python :: 3.10
Classifier: Programming Language :: Python :: 3.11
Requires-Dist: pylint (>=1.7)
Project-URL: Repository, https://github.com/PyCQA/pylint-plugin-utils
